piodispatch/__init__.py
piodispatch/piodispatch.py
piodispatch/test_piodispatch.py
piodispatch-1.0.3.dist-info/LICENSE
piodispatch-1.0.3.dist-info/METADATA
piodispatch-1.0.3.dist-info/WHEEL
piodispatch-1.0.3.dist-info/top_level.txt
piodispatch-1.0.3.dist-info/RECORD
