Metadata-Version: 2.1
Name: piodispatch
Version: 1.0.3
Summary: Dispatch blocking IO calls to threads wrapped in coroutines.
Home-page: https://github.com/Kiruse/PioDispatch
Author: Kiruse
Author-email: neurokiruse@outlook.com
License: MIT
Keywords: asyncio,threading,async,await
Platform: UNKNOWN
Requires-Python: >=3.7
